{
  "cat_name": "Saba",
  "robot_name": "scoopy",
  "generated_at": "2026-01-25T12:04:13.759368-08:00",
  "weight_average": 11.0,
  "weight_min": 10.7,
  "weight_max": 11.3,
  "weight_trend": "stable",
  "weight_change": -0.02,
  "weight_change_abs": 0.02,
  "date_range_display": "Jan 18 - Jan 25, 2026",
  "peak_hour_display": "10:00 AM",
  "date_range": {
    "start": "Jan 18",
    "end": "Jan 25, 2026",
    "display": "Jan 18 - Jan 25, 2026"
  },
  "personality_traits": [
    "Early Bird",
    "Weekday Regular"
  ],
  "total_visits": 19,
  "visits_per_day": 2.8,
  "chart_data": [
    {
      "weekday": "Sun",
      "display": "01/18",
      "count": 1
    },
    {
      "weekday": "Mon",
      "display": "01/19",
      "count": 3
    },
    {
      "weekday": "Tue",
      "display": "01/20",
      "count": 3
    },
    {
      "weekday": "Wed",
      "display": "01/21",
      "count": 2
    },
    {
      "weekday": "Thu",
      "display": "01/22",
      "count": 3
    },
    {
      "weekday": "Fri",
      "display": "01/23",
      "count": 4
    },
    {
      "weekday": "Sat",
      "display": "01/24",
      "count": 2
    },
    {
      "weekday": "Sun",
      "display": "01/25",
      "count": 1
    }
  ],
  "weight_history": [
    {
      "display": "01/18",
      "weight": 11.0
    },
    {
      "display": "01/19",
      "weight": 11.1
    },
    {
      "display": "01/20",
      "weight": 11.0
    },
    {
      "display": "01/21",
      "weight": 10.7
    },
    {
      "display": "01/22",
      "weight": 10.9
    },
    {
      "display": "01/23",
      "weight": 11.0
    },
    {
      "display": "01/24",
      "weight": 11.0
    },
    {
      "display": "01/25",
      "weight": 11.0
    }
  ],
  "timing": {
    "longest_gap": "16h 25m",
    "shortest_gap": "1h 50m"
  },
  "weight": {
    "average": 11.0,
    "min": 10.7,
    "max": 11.3,
    "trend": "stable",
    "change": -0.02
  },
  "peak_hour": {
    "hour": 10,
    "count": 3,
    "display": "10:00 AM"
  },
  "busiest_date": {
    "day_name": "Friday",
    "display": "01/23",
    "count": 4,
    "is_weekend": false
  },
  "robot_stats": {
    "clean_cycles": 19,
    "interruptions": 0
  },
  "output": {
    "oz": 48.0,
    "lbs": 3.0
  }
}